{
  "nextId": 15,
  "notes": {
    "2": {
      "id": 2,
      "content": "meow"
    },
    "5": {
      "id": 5,
      "content": "In JavaScript, the value of `this` is determined when a function is called; not when it is defined."
    },
    "6": {
      "id": 6,
      "content": "A closure is formed when a function retains access to variables in its lexical scope."
    },
    "9": {
      "id": 9,
      "content": "Inertia is a property of matter."
    },
    "10": {
      "id": 10,
      "content": "test"
    },
    "11": {
      "id": 11,
      "content": "test"
    },
    "12": {
      "id": 12,
      "content": "meow"
    },
    "13": {
      "id": 13,
      "content": "hello"
    },
    "14": {
      "id": 14,
      "content": "sunshine"
    }
  }
}